iamsystem/__init__.py
iamsystem/brat/__init__.py
iamsystem/brat/adapter.py
iamsystem/brat/formatter.py
iamsystem/brat/util.py
iamsystem/fuzzy/__init__.py
iamsystem/fuzzy/abbreviations.py
iamsystem/fuzzy/api.py
iamsystem/fuzzy/cache.py
iamsystem/fuzzy/exact.py
iamsystem/fuzzy/norm_fun.py
iamsystem/fuzzy/regex.py
iamsystem/fuzzy/simstring.py
iamsystem/fuzzy/spellwise.py
iamsystem/fuzzy/util.py
iamsystem/keywords/__init__.py
iamsystem/keywords/api.py
iamsystem/keywords/collection.py
iamsystem/keywords/keywords.py
iamsystem/keywords/util.py
iamsystem/matcher/__init__.py
iamsystem/matcher/annotation.py
iamsystem/matcher/api.py
iamsystem/matcher/matcher.py
iamsystem/matcher/printannot.py
iamsystem/matcher/strategy.py
iamsystem/matcher/util.py
iamsystem/spacy/__init__.py
iamsystem/spacy/component.py
iamsystem/spacy/stopwords.py
iamsystem/spacy/token.py
iamsystem/spacy/tokenizer.py
iamsystem/stopwords/__init__.py
iamsystem/stopwords/api.py
iamsystem/stopwords/negative.py
iamsystem/stopwords/simple.py
iamsystem/tokenization/__init__.py
iamsystem/tokenization/api.py
iamsystem/tokenization/normalize.py
iamsystem/tokenization/span.py
iamsystem/tokenization/token.py
iamsystem/tokenization/tokenize.py
iamsystem/tokenization/util.py
iamsystem/tree/__init__.py
iamsystem/tree/api.py
iamsystem/tree/nodes.py
iamsystem/tree/trie.py
iamsystem-0.6.1.dist-info/LICENSE
iamsystem-0.6.1.dist-info/METADATA
iamsystem-0.6.1.dist-info/WHEEL
iamsystem-0.6.1.dist-info/top_level.txt
iamsystem-0.6.1.dist-info/RECORD
