Metadata-Version: 2.1
Name: iamsystem
Version: 0.6.1
Summary: A python implementation of IAMsystem algorithm
Author-email: Sebastien Cossin <cossin.sebastien@gmail.com>
Project-URL: Homepage, https://github.com/scossin/iamsystem_python
Project-URL: Bug Tracker, https://github.com/scossin/iamsystem_python/issues
Keywords: NLP,semantic annotation,entity linking
Classifier: Development Status :: 4 - Beta
Classifier: Programming Language :: Python :: 3.7
Classifier: Programming Language :: Python :: 3.8
Classifier: Programming Language :: Python :: 3.9
Classifier: Programming Language :: Python :: 3.10
Classifier: Programming Language :: Python :: 3.11
Classifier: Programming Language :: Python :: 3.12
Classifier: License :: OSI Approved :: MIT License
Classifier: Operating System :: OS Independent
Requires-Python: >=3.7
License-File: LICENSE
Requires-Dist: anyascii
Requires-Dist: pysimstring
Requires-Dist: spellwise
Requires-Dist: typing-extensions
Provides-Extra: dev
Requires-Dist: black ; extra == 'dev'
Requires-Dist: flake8 ; extra == 'dev'
Requires-Dist: pre-commit ; extra == 'dev'
Provides-Extra: doc
Requires-Dist: sphinx ; extra == 'doc'
Requires-Dist: sphinx-rtd-theme ; extra == 'doc'
Provides-Extra: tests
Requires-Dist: nltk ; extra == 'tests'
Requires-Dist: spacy ; extra == 'tests'
